ai_dev_manager_mcp/__init__.py
ai_dev_manager_mcp/main.py
ai_dev_manager_mcp/models.py
ai_dev_manager_mcp/services.py
ai_dev_manager_mcp-0.1.1.dist-info/METADATA
ai_dev_manager_mcp-0.1.1.dist-info/WHEEL
ai_dev_manager_mcp-0.1.1.dist-info/entry_points.txt
ai_dev_manager_mcp-0.1.1.dist-info/licenses/LICENSE
ai_dev_manager_mcp-0.1.1.dist-info/RECORD
