Metadata-Version: 2.4
Name: ai-dev-manager-mcp
Version: 0.1.1
Summary: AI开发经理MCP服务 - 智能开发流程管理工具
Project-URL: Homepage, https://github.com/yourusername/ai-dev-manager-mcp
Project-URL: Repository, https://github.com/yourusername/ai-dev-manager-mcp
Project-URL: Documentation, https://github.com/yourusername/ai-dev-manager-mcp#readme
Project-URL: Bug Tracker, https://github.com/yourusername/ai-dev-manager-mcp/issues
Author-email: Your Name <your.email@example.com>
License-Expression: MIT
License-File: LICENSE
Keywords: ai,claude,development,mcp,project-management
Classifier: Development Status :: 4 - Beta
Classifier: Intended Audience :: Developers
Classifier: License :: OSI Approved :: MIT License
Classifier: Programming Language :: Python :: 3
Classifier: Programming Language :: Python :: 3.8
Classifier: Programming Language :: Python :: 3.9
Classifier: Programming Language :: Python :: 3.10
Classifier: Programming Language :: Python :: 3.11
Classifier: Programming Language :: Python :: 3.12
Classifier: Topic :: Software Development
Classifier: Topic :: Software Development :: Documentation
Classifier: Topic :: Software Development :: Libraries :: Python Modules
Requires-Python: >=3.8
Requires-Dist: click>=8.0.0
Requires-Dist: fastmcp>=0.15.0
Requires-Dist: pydantic>=2.0.0
Requires-Dist: semantic-version>=2.10.0
Requires-Dist: typing-extensions>=4.5.0
Provides-Extra: dev
Requires-Dist: black>=23.0.0; extra == 'dev'
Requires-Dist: flake8>=6.0.0; extra == 'dev'
Requires-Dist: mypy>=1.0.0; extra == 'dev'
Requires-Dist: pytest>=7.0.0; extra == 'dev'
